{"items":[{"children":[],"data":{"tag":"UI.Track.UrlD","contents":{"url":"https://en.wikipedia.org/wiki/Catherine_of_Siena"}},"expanded":false,"subtitle":"St. Catherine Of Siena","title":"St. Catherine Of Siena (Wiki)","view":{"tag":"UI.ContentViews.Views.WebView"}},{"children":[],"data":{"tag":"UI.Track.UrlD","contents":{"url":"https://archive.org/stream/StCatherineOfSienaAndHerTimes"}},"expanded":false,"subtitle":"St. Catherine of Siena And Her Times","title":"St. Catherine Of Siena / Roberts","view":{"tag":"UI.ContentViews.Views.WebView"}},{"children":[],"data":{"tag":"UI.Track.UrlD","contents":{"url":"https://archive.org/stream/historystcatheri01dranuoft"}},"expanded":false,"subtitle":"The History of /and Companions","title":"St. Catherine Of Siena / Drane","view":{"tag":"UI.ContentViews.Views.WebView"}},{"children":[],"data":{"tag":"UI.Track.UrlD","contents":{"url":"https://archive.org/stream/in.ernet.dli.2015.70659"}},"expanded":false,"subtitle":"Saint Catherine Of Siena","title":"St. Catherine Of Siena/ Jorgensen","view":{"tag":"UI.ContentViews.Views.WebView"}},{"children":[],"data":{"tag":"UI.Track.UrlD","contents":{"url":"https://archive.org/stream/SaintCatherineOfSienaAsSeenInHerLetters"}},"expanded":true,"subtitle":"As Seen In Her Letters","title":"St. Catherine Of Siena","view":{"tag":"UI.ContentViews.Views.WebView"}},{"children":[],"data":{"tag":"UI.Track.UrlD","contents":{"url":"https://archive.org/details/CathDialog1"}},"expanded":true,"subtitle":"The Dialogue Part 1","title":"St. Catherine Of Siena (Audio)","view":{"tag":"UI.ContentViews.Views.WebView"}},{"children":[],"data":{"tag":"UI.Track.UrlD","contents":{"url":"https://archive.org/details/CDialog2"}},"expanded":false,"subtitle":"The Dialogue Part 2","title":"St. Catherine Of Siena (Audio)","view":{"tag":"UI.ContentViews.Views.WebView"}},{"children":[],"data":{"tag":"UI.Track.UrlD","contents":{"url":"https://archive.org/details/cdialog3"}},"expanded":false,"subtitle":"The Dialogue Part 3","title":"St. Catherine Of Siena (Audio)","view":{"tag":"UI.ContentViews.Views.WebView"}},{"children":[],"data":{"tag":"UI.Track.UrlD","contents":{"url":"https://archive.org/details/CDialog4"}},"expanded":false,"subtitle":"The Dialogue Part 4","title":"St. Catherine Of Siena (Audio)","view":{"tag":"UI.ContentViews.Views.WebView"}},{"children":[],"data":{"tag":"UI.Track.UrlD","contents":{"url":"https://archive.org/details/CDialog5"}},"expanded":true,"subtitle":"The Dialogue Part 5","title":"St. Catherine Of Siena (Audio)","view":{"tag":"UI.ContentViews.Views.WebView"}}]}